chercher_plugin_docx/__init__.py
chercher_plugin_docx-0.1.3.dist-info/licenses/LICENSE
chercher_plugin_docx-0.1.3.dist-info/METADATA
chercher_plugin_docx-0.1.3.dist-info/WHEEL
chercher_plugin_docx-0.1.3.dist-info/entry_points.txt
chercher_plugin_docx-0.1.3.dist-info/top_level.txt
chercher_plugin_docx-0.1.3.dist-info/RECORD
